setup.py
nodejs/__init__.py
nodejs/bindings.py
nodejs/conf.py
nodejs/exceptions.py
nodejs/interrogate.py
nodejs.egg-info/PKG-INFO
nodejs.egg-info/SOURCES.txt
nodejs.egg-info/dependency_links.txt
nodejs.egg-info/top_level.txt
nodejs/utils/__init__.py
nodejs/utils/conf/__init__.py
nodejs/utils/six/__init__.py