Metadata-Version: 1.0
Name: nodejs
Version: 0.1.0
Summary: Python bindings and utils for Node.js and io.js
Home-page: https://github.com/markfinger/python-nodejs
Author: Mark Finger
Author-email: markfinger@gmail.com
License: UNKNOWN
Platform: UNKNOWN
